{
  "keyword": "演示关键词 / 服务安装样例",
  "updated_at": "2026-03-02 17:49:13",
  "notes": [
    {
      "id": "demo-note-001",
      "title": "演示笔记：养生赛道内容看板",
      "cover_image": "",
      "reads": 0,
      "likes": 16499,
      "saves": 18729,
      "comments": 97,
      "shares": 2573,
      "publish_date": "示例",
      "tags": "演示,看板",
      "blogger_name": "示例博主",
      "blogger_avatar": "",
      "blogger_bio": "",
      "followers": 0,
      "note_url": "https://www.xiaohongshu.com/explore/demo-note-001"
    },
    {
      "id": "demo-note-002",
      "title": "演示笔记：食疗内容趋势",
      "cover_image": "",
      "reads": 0,
      "likes": 8430,
      "saves": 6910,
      "comments": 68,
      "shares": 420,
      "publish_date": "示例",
      "tags": "演示,趋势",
      "blogger_name": "示例账号",
      "blogger_avatar": "",
      "blogger_bio": "",
      "followers": 0,
      "note_url": "https://www.xiaohongshu.com/explore/demo-note-002"
    }
  ]
}
